{
  "base_spec": "/pa/ammo/base_shell/base_shell.json",
  "damage": 1000,
  "fx_trail": {
    "filename": "/pa/units/land/L_sniper_tank/trail.pfx",
    "offset": [
      0,
      0,
      0
    ]
  },
  "events": {
    "died": {
      "audio_cue": "/SE/Impacts/missile_artillery_long_holkins",
      "effect_spec": "/pa/units/land/L_sniper_tank/hit.pfx"
    }
  },
  "physics": {
	"radius": 1,
	"gravity_scalar": 26,
	"add_to_spatial_db": false,
	"allow_underground": true
  },
  "initial_velocity": 200,
  "lifetime": 3,
  "min_velocity": 90,
  "max_velocity": 500,
  "splash_damage": 0,
  "splash_radius": 0
}
